cmne/__init__.py
cmne/_version.py
cmne/data.py
cmne/example.py
cmne/settings.py
cmne/train.py
cmne-0.1.0.dist-info/LICENSE
cmne-0.1.0.dist-info/METADATA
cmne-0.1.0.dist-info/WHEEL
cmne-0.1.0.dist-info/top_level.txt
cmne-0.1.0.dist-info/RECORD
