Metadata-Version: 2.1
Name: cmne
Version: 0.1.0
Summary: Contextual Minimum Norm Estimates (CMNE)
Home-page: https://github.com/chdinh/cmne
Maintainer: Christoph Dinh
Maintainer-email: christoph.dinh@brain-link.de
License: MIT License
Download-URL: https://github.com/chdinh/cmne
Project-URL: Source, https://github.com/chdinh/cmne/
Project-URL: Tracker, https://github.com/chdinh/cmne/issues/
Keywords: MEG EEG spatiotemporal source estimation spatial filtering grid-based Markov localization LSTM deep learning
Platform: any
Classifier: Intended Audience :: Science/Research
Classifier: Intended Audience :: Developers
Classifier: License :: OSI Approved :: MIT License
Classifier: Topic :: Scientific/Engineering
Classifier: Programming Language :: Python :: 3
Classifier: Development Status :: 1 - Planning
Classifier: Operating System :: OS Independent
Requires-Python: >=3.7
Requires-Dist: numpy (>=1.21.2)
Requires-Dist: mne (>=0.23.4)
Requires-Dist: tensorflow (>=2.6.0)
Requires-Dist: matplotlib (>=3.5.1)
Requires-Dist: pandas (>=1.4.1)
Requires-Dist: pooch (>=1.6.0)
